emsa/__init__.py
emsa/dataloader.py
emsa/plotter.py
emsa/simulation_base.py
emsa/model/__init__.py
emsa/model/epidemic_model.py
emsa/model/matrix_generator.py
emsa/model/model_base.py
emsa/model/r0.py
emsa/sensitivity/__init__.py
emsa/sensitivity/prcc.py
emsa/sensitivity/sampler_base.py
emsa/sensitivity/sensitivity_model_base.py
emsa/sensitivity/target_calc/__init__.py
emsa/sensitivity/target_calc/output_generator.py
emsa/sensitivity/target_calc/r0calculator.py
emsa/sensitivity/target_calc/sol_based_target_calc.py
emsa_examples/__init__.py
emsa_examples/SEIHR_2_age_groups/__init__.py
emsa_examples/SEIHR_2_age_groups/seihr_2_ag_main.py
emsa_examples/SEIHR_2_age_groups/simulation_seihr.py
emsa_examples/SEIR_no_age_groups/__init__.py
emsa_examples/SEIR_no_age_groups/model_seir.py
emsa_examples/SEIR_no_age_groups/sampler_seir.py
emsa_examples/SEIR_no_age_groups/seir_no_ag_main.py
emsa_examples/SEIR_no_age_groups/simulation_seir.py
emsa_examples/contact_sensitivity/__init__.py
emsa_examples/contact_sensitivity/contact_main.py
emsa_examples/contact_sensitivity/sampler_contact.py
emsa_examples/contact_sensitivity/sensitivity_model_contact.py
emsa_examples/contact_sensitivity/simulation_contact.py
emsa_examples/utils/__init__.py
emsa_examples/utils/dataloader_16_ag.py
emsa_examples/vaccinated_sensitivity/__init__.py
emsa_examples/vaccinated_sensitivity/sampler_vaccinated.py
emsa_examples/vaccinated_sensitivity/sensitivity_model_vaccinated.py
emsa_examples/vaccinated_sensitivity/simulation_vacc.py
emsa_examples/vaccinated_sensitivity/vaccinated_main.py
epimodel_sensitivity_test-0.1.17.dist-info/METADATA
epimodel_sensitivity_test-0.1.17.dist-info/WHEEL
epimodel_sensitivity_test-0.1.17.dist-info/top_level.txt
epimodel_sensitivity_test-0.1.17.dist-info/RECORD
