Metadata-Version: 2.1
Name: epimodel_sensitivity_test
Version: 0.1.17
Summary: Efficient sensitivity analysis and evaluation of epidemiological models
Home-page: https://github.com/KKol21/epimodel_sensitivity
Author: Kolos Kovács
Author-email: kovkol21@gmail.com
Classifier: Programming Language :: Python :: 3
Classifier: Operating System :: OS Independent
Requires-Dist: smt ~=1.3.0
Requires-Dist: tqdm
Requires-Dist: xlrd ==1.2.0
Requires-Dist: torchode ~=0.2.0
